example_pkg/__init__.py
alondra-0.0.0.dist-info/LICENSE
alondra-0.0.0.dist-info/METADATA
alondra-0.0.0.dist-info/WHEEL
alondra-0.0.0.dist-info/top_level.txt
alondra-0.0.0.dist-info/RECORD
