Metadata-Version: 2.1
Name: alondra
Version: 0.0.0
Summary: An example Python project
Author: Simon
License-File: LICENSE
Requires-Dist: requests
Requires-Dist: numpy
